charpe/__init__.py
charpe/errors.py
charpe/handler.py
charpe/loop.py
charpe/main.py
charpe/settings.py
charpe/template_filters.py
charpe/version.txt
charpe/mediums/__init__.py
charpe/mediums/base.py
charpe/mediums/email_handler.py
charpe/mediums/telegram_handler.py
charpe/templates/assigned-task.html
charpe/templates/basic.html
charpe/templates/server-error.html
charpe-1.1.1.dist-info/METADATA
charpe-1.1.1.dist-info/RECORD
charpe-1.1.1.dist-info/WHEEL
charpe-1.1.1.dist-info/entry_points.txt
charpe-1.1.1.dist-info/top_level.txt
