Metadata-Version: 2.1
Name: charpe
Version: 1.1.1
Summary: Sends messages from applications through different media
Home-page: https://github.com/tracsa/charpe
Author: Abraham Toriz Cruz
Author-email: categulario@gmail.com
License: MIT
Keywords: notification
Platform: UNKNOWN
Classifier: Development Status :: 4 - Beta
Classifier: Intended Audience :: Developers
Classifier: Topic :: Software Development :: Libraries :: Python Modules
Classifier: License :: OSI Approved :: MIT License
Classifier: Programming Language :: Python :: 3
Classifier: Programming Language :: Python :: 3.6
Requires-Dist: jinja2
Requires-Dist: simplejson
Requires-Dist: requests
Requires-Dist: pika
Requires-Dist: itacate
Requires-Dist: pytz
Requires-Dist: case-conversion
